{"frames": {

"blob.png":
{
	"frame": {"x":288,"y":80,"w":32,"h":32},
	"rotated": false,
	"trimmed": false,
	"spriteSourceSize": {"x":0,"y":0,"w":32,"h":32},
	"sourceSize": {"w":32,"h":32}
},
"blob_dead_1.png":
{
	"frame": {"x":320,"y":80,"w":32,"h":32},
	"rotated": false,
	"trimmed": false,
	"spriteSourceSize": {"x":0,"y":0,"w":32,"h":32},
	"sourceSize": {"w":32,"h":32}
},
"blob_idle_1.png":
{
	"frame": {"x":256,"y":80,"w":32,"h":32},
	"rotated": false,
	"trimmed": false,
	"spriteSourceSize": {"x":0,"y":0,"w":32,"h":32},
	"sourceSize": {"w":32,"h":32}
},
"blob_idle_2.png":
{
	"frame": {"x":352,"y":80,"w":32,"h":32},
	"rotated": false,
	"trimmed": false,
	"spriteSourceSize": {"x":0,"y":0,"w":32,"h":32},
	"sourceSize": {"w":32,"h":32}
},
"blob_move_enemy_1.png":
{
	"frame": {"x":384,"y":80,"w":32,"h":32},
	"rotated": false,
	"trimmed": false,
	"spriteSourceSize": {"x":0,"y":0,"w":32,"h":32},
	"sourceSize": {"w":32,"h":32}
},
"blob_move_friendly_1.png":
{
	"frame": {"x":32,"y":112,"w":32,"h":32},
	"rotated": false,
	"trimmed": false,
	"spriteSourceSize": {"x":0,"y":0,"w":32,"h":32},
	"sourceSize": {"w":32,"h":32}
},
"character_ui_base.png":
{
	"frame": {"x":0,"y":16,"w":32,"h":8},
	"rotated": false,
	"trimmed": false,
	"spriteSourceSize": {"x":0,"y":0,"w":32,"h":8},
	"sourceSize": {"w":32,"h":8}
},
"character_ui_base2.png":
{
	"frame": {"x":350,"y":0,"w":32,"h":8},
	"rotated": false,
	"trimmed": false,
	"spriteSourceSize": {"x":0,"y":0,"w":32,"h":8},
	"sourceSize": {"w":32,"h":8}
},
"character_ui_hp.png":
{
	"frame": {"x":17,"y":0,"w":13,"h":2},
	"rotated": false,
	"trimmed": false,
	"spriteSourceSize": {"x":0,"y":0,"w":13,"h":2},
	"sourceSize": {"w":13,"h":2}
},
"character_ui_icon_attack.png":
{
	"frame": {"x":318,"y":0,"w":32,"h":8},
	"rotated": false,
	"trimmed": false,
	"spriteSourceSize": {"x":0,"y":0,"w":32,"h":8},
	"sourceSize": {"w":32,"h":8}
},
"character_ui_icon_defend.png":
{
	"frame": {"x":382,"y":0,"w":32,"h":8},
	"rotated": false,
	"trimmed": false,
	"spriteSourceSize": {"x":0,"y":0,"w":32,"h":8},
	"sourceSize": {"w":32,"h":8}
},
"character_ui_icon_skull.png":
{
	"frame": {"x":64,"y":16,"w":32,"h":8},
	"rotated": false,
	"trimmed": false,
	"spriteSourceSize": {"x":0,"y":0,"w":32,"h":8},
	"sourceSize": {"w":32,"h":8}
},
"character_ui_icon_special.png":
{
	"frame": {"x":96,"y":16,"w":32,"h":8},
	"rotated": false,
	"trimmed": false,
	"spriteSourceSize": {"x":0,"y":0,"w":32,"h":8},
	"sourceSize": {"w":32,"h":8}
},
"character_ui_icon_unknown.png":
{
	"frame": {"x":32,"y":16,"w":32,"h":8},
	"rotated": false,
	"trimmed": false,
	"spriteSourceSize": {"x":0,"y":0,"w":32,"h":8},
	"sourceSize": {"w":32,"h":8}
},
"character_ui_sp.png":
{
	"frame": {"x":4,"y":0,"w":13,"h":1},
	"rotated": false,
	"trimmed": false,
	"spriteSourceSize": {"x":0,"y":0,"w":13,"h":1},
	"sourceSize": {"w":13,"h":1}
},
"icon.png":
{
	"frame": {"x":0,"y":176,"w":256,"h":256},
	"rotated": false,
	"trimmed": false,
	"spriteSourceSize": {"x":0,"y":0,"w":256,"h":256},
	"sourceSize": {"w":256,"h":256}
},
"palette.png":
{
	"frame": {"x":0,"y":0,"w":4,"h":5},
	"rotated": false,
	"trimmed": false,
	"spriteSourceSize": {"x":0,"y":0,"w":4,"h":5},
	"sourceSize": {"w":4,"h":5}
},
"pointer.png":
{
	"frame": {"x":64,"y":112,"w":32,"h":32},
	"rotated": false,
	"trimmed": false,
	"spriteSourceSize": {"x":0,"y":0,"w":32,"h":32},
	"sourceSize": {"w":32,"h":32}
},
"punchy_dead_1.png":
{
	"frame": {"x":0,"y":112,"w":32,"h":32},
	"rotated": false,
	"trimmed": false,
	"spriteSourceSize": {"x":0,"y":0,"w":32,"h":32},
	"sourceSize": {"w":32,"h":32}
},
"punchy_dead_2.png":
{
	"frame": {"x":224,"y":80,"w":32,"h":32},
	"rotated": false,
	"trimmed": false,
	"spriteSourceSize": {"x":0,"y":0,"w":32,"h":32},
	"sourceSize": {"w":32,"h":32}
},
"punchy_idle_1.png":
{
	"frame": {"x":192,"y":80,"w":32,"h":32},
	"rotated": false,
	"trimmed": false,
	"spriteSourceSize": {"x":0,"y":0,"w":32,"h":32},
	"sourceSize": {"w":32,"h":32}
},
"punchy_idle_2.png":
{
	"frame": {"x":352,"y":48,"w":32,"h":32},
	"rotated": false,
	"trimmed": false,
	"spriteSourceSize": {"x":0,"y":0,"w":32,"h":32},
	"sourceSize": {"w":32,"h":32}
},
"punchy_idle_3.png":
{
	"frame": {"x":384,"y":48,"w":32,"h":32},
	"rotated": false,
	"trimmed": false,
	"spriteSourceSize": {"x":0,"y":0,"w":32,"h":32},
	"sourceSize": {"w":32,"h":32}
},
"punchy_idle_4.png":
{
	"frame": {"x":32,"y":80,"w":32,"h":32},
	"rotated": false,
	"trimmed": false,
	"spriteSourceSize": {"x":0,"y":0,"w":32,"h":32},
	"sourceSize": {"w":32,"h":32}
},
"punchy_move_enemy_1.png":
{
	"frame": {"x":64,"y":80,"w":32,"h":32},
	"rotated": false,
	"trimmed": false,
	"spriteSourceSize": {"x":0,"y":0,"w":32,"h":32},
	"sourceSize": {"w":32,"h":32}
},
"punchy_move_enemy_2.png":
{
	"frame": {"x":128,"y":80,"w":32,"h":32},
	"rotated": false,
	"trimmed": false,
	"spriteSourceSize": {"x":0,"y":0,"w":32,"h":32},
	"sourceSize": {"w":32,"h":32}
},
"punchy_move_enemy_3.png":
{
	"frame": {"x":160,"y":80,"w":32,"h":32},
	"rotated": false,
	"trimmed": false,
	"spriteSourceSize": {"x":0,"y":0,"w":32,"h":32},
	"sourceSize": {"w":32,"h":32}
},
"punchy_move_enemy_4.png":
{
	"frame": {"x":96,"y":112,"w":32,"h":32},
	"rotated": false,
	"trimmed": false,
	"spriteSourceSize": {"x":0,"y":0,"w":32,"h":32},
	"sourceSize": {"w":32,"h":32}
},
"punchy_move_enemy_5.png":
{
	"frame": {"x":0,"y":80,"w":32,"h":32},
	"rotated": false,
	"trimmed": false,
	"spriteSourceSize": {"x":0,"y":0,"w":32,"h":32},
	"sourceSize": {"w":32,"h":32}
},
"punchy_move_enemy_6.png":
{
	"frame": {"x":192,"y":112,"w":32,"h":32},
	"rotated": false,
	"trimmed": false,
	"spriteSourceSize": {"x":0,"y":0,"w":32,"h":32},
	"sourceSize": {"w":32,"h":32}
},
"punchy_move_enemy_7.png":
{
	"frame": {"x":64,"y":144,"w":32,"h":32},
	"rotated": false,
	"trimmed": false,
	"spriteSourceSize": {"x":0,"y":0,"w":32,"h":32},
	"sourceSize": {"w":32,"h":32}
},
"punchy_move_enemy_8.png":
{
	"frame": {"x":96,"y":144,"w":32,"h":32},
	"rotated": false,
	"trimmed": false,
	"spriteSourceSize": {"x":0,"y":0,"w":32,"h":32},
	"sourceSize": {"w":32,"h":32}
},
"punchy_move_friendly_1.png":
{
	"frame": {"x":32,"y":144,"w":32,"h":32},
	"rotated": false,
	"trimmed": false,
	"spriteSourceSize": {"x":0,"y":0,"w":32,"h":32},
	"sourceSize": {"w":32,"h":32}
},
"skele_dead_1.png":
{
	"frame": {"x":128,"y":144,"w":32,"h":32},
	"rotated": false,
	"trimmed": false,
	"spriteSourceSize": {"x":0,"y":0,"w":32,"h":32},
	"sourceSize": {"w":32,"h":32}
},
"skele_idle_1.png":
{
	"frame": {"x":192,"y":144,"w":32,"h":32},
	"rotated": false,
	"trimmed": false,
	"spriteSourceSize": {"x":0,"y":0,"w":32,"h":32},
	"sourceSize": {"w":32,"h":32}
},
"skele_idle_2.png":
{
	"frame": {"x":256,"y":144,"w":32,"h":32},
	"rotated": false,
	"trimmed": false,
	"spriteSourceSize": {"x":0,"y":0,"w":32,"h":32},
	"sourceSize": {"w":32,"h":32}
},
"skele_idle_3.png":
{
	"frame": {"x":224,"y":144,"w":32,"h":32},
	"rotated": false,
	"trimmed": false,
	"spriteSourceSize": {"x":0,"y":0,"w":32,"h":32},
	"sourceSize": {"w":32,"h":32}
},
"skele_idle_4.png":
{
	"frame": {"x":160,"y":144,"w":32,"h":32},
	"rotated": false,
	"trimmed": false,
	"spriteSourceSize": {"x":0,"y":0,"w":32,"h":32},
	"sourceSize": {"w":32,"h":32}
},
"skele_move_enemy_1.png":
{
	"frame": {"x":0,"y":144,"w":32,"h":32},
	"rotated": false,
	"trimmed": false,
	"spriteSourceSize": {"x":0,"y":0,"w":32,"h":32},
	"sourceSize": {"w":32,"h":32}
},
"skele_move_enemy_2.png":
{
	"frame": {"x":384,"y":112,"w":32,"h":32},
	"rotated": false,
	"trimmed": false,
	"spriteSourceSize": {"x":0,"y":0,"w":32,"h":32},
	"sourceSize": {"w":32,"h":32}
},
"skele_move_enemy_3.png":
{
	"frame": {"x":128,"y":112,"w":32,"h":32},
	"rotated": false,
	"trimmed": false,
	"spriteSourceSize": {"x":0,"y":0,"w":32,"h":32},
	"sourceSize": {"w":32,"h":32}
},
"skele_move_enemy_4.png":
{
	"frame": {"x":160,"y":112,"w":32,"h":32},
	"rotated": false,
	"trimmed": false,
	"spriteSourceSize": {"x":0,"y":0,"w":32,"h":32},
	"sourceSize": {"w":32,"h":32}
},
"skele_move_friendly_1.png":
{
	"frame": {"x":224,"y":112,"w":32,"h":32},
	"rotated": false,
	"trimmed": false,
	"spriteSourceSize": {"x":0,"y":0,"w":32,"h":32},
	"sourceSize": {"w":32,"h":32}
},
"soldier_dead_1.png":
{
	"frame": {"x":320,"y":48,"w":32,"h":32},
	"rotated": false,
	"trimmed": false,
	"spriteSourceSize": {"x":0,"y":0,"w":32,"h":32},
	"sourceSize": {"w":32,"h":32}
},
"soldier_dead_2.png":
{
	"frame": {"x":320,"y":112,"w":32,"h":32},
	"rotated": false,
	"trimmed": false,
	"spriteSourceSize": {"x":0,"y":0,"w":32,"h":32},
	"sourceSize": {"w":32,"h":32}
},
"soldier_dead_3.png":
{
	"frame": {"x":352,"y":112,"w":32,"h":32},
	"rotated": false,
	"trimmed": false,
	"spriteSourceSize": {"x":0,"y":0,"w":32,"h":32},
	"sourceSize": {"w":32,"h":32}
},
"soldier_idle_1.png":
{
	"frame": {"x":288,"y":112,"w":32,"h":32},
	"rotated": false,
	"trimmed": false,
	"spriteSourceSize": {"x":0,"y":0,"w":32,"h":32},
	"sourceSize": {"w":32,"h":32}
},
"soldier_idle_2.png":
{
	"frame": {"x":96,"y":80,"w":32,"h":32},
	"rotated": false,
	"trimmed": false,
	"spriteSourceSize": {"x":0,"y":0,"w":32,"h":32},
	"sourceSize": {"w":32,"h":32}
},
"soldier_idle_3.png":
{
	"frame": {"x":0,"y":48,"w":32,"h":32},
	"rotated": false,
	"trimmed": false,
	"spriteSourceSize": {"x":0,"y":0,"w":32,"h":32},
	"sourceSize": {"w":32,"h":32}
},
"soldier_idle_4.png":
{
	"frame": {"x":160,"y":16,"w":32,"h":32},
	"rotated": false,
	"trimmed": false,
	"spriteSourceSize": {"x":0,"y":0,"w":32,"h":32},
	"sourceSize": {"w":32,"h":32}
},
"soldier_move_enemy_1.png":
{
	"frame": {"x":224,"y":16,"w":32,"h":32},
	"rotated": false,
	"trimmed": false,
	"spriteSourceSize": {"x":0,"y":0,"w":32,"h":32},
	"sourceSize": {"w":32,"h":32}
},
"soldier_move_enemy_2.png":
{
	"frame": {"x":320,"y":16,"w":32,"h":32},
	"rotated": false,
	"trimmed": false,
	"spriteSourceSize": {"x":0,"y":0,"w":32,"h":32},
	"sourceSize": {"w":32,"h":32}
},
"soldier_move_enemy_3.png":
{
	"frame": {"x":256,"y":16,"w":32,"h":32},
	"rotated": false,
	"trimmed": false,
	"spriteSourceSize": {"x":0,"y":0,"w":32,"h":32},
	"sourceSize": {"w":32,"h":32}
},
"soldier_move_enemy_4.png":
{
	"frame": {"x":288,"y":16,"w":32,"h":32},
	"rotated": false,
	"trimmed": false,
	"spriteSourceSize": {"x":0,"y":0,"w":32,"h":32},
	"sourceSize": {"w":32,"h":32}
},
"soldier_move_friendly_1.png":
{
	"frame": {"x":192,"y":16,"w":32,"h":32},
	"rotated": false,
	"trimmed": false,
	"spriteSourceSize": {"x":0,"y":0,"w":32,"h":32},
	"sourceSize": {"w":32,"h":32}
},
"soldier_move_friendly_2.png":
{
	"frame": {"x":128,"y":16,"w":32,"h":32},
	"rotated": false,
	"trimmed": false,
	"spriteSourceSize": {"x":0,"y":0,"w":32,"h":32},
	"sourceSize": {"w":32,"h":32}
},
"tile_blank.png":
{
	"frame": {"x":286,"y":0,"w":16,"h":16},
	"rotated": false,
	"trimmed": false,
	"spriteSourceSize": {"x":0,"y":0,"w":16,"h":16},
	"sourceSize": {"w":16,"h":16}
},
"tile_clouds_1.png":
{
	"frame": {"x":30,"y":0,"w":16,"h":16},
	"rotated": false,
	"trimmed": false,
	"spriteSourceSize": {"x":0,"y":0,"w":16,"h":16},
	"sourceSize": {"w":16,"h":16}
},
"tile_floor_1.png":
{
	"frame": {"x":46,"y":0,"w":16,"h":16},
	"rotated": false,
	"trimmed": false,
	"spriteSourceSize": {"x":0,"y":0,"w":16,"h":16},
	"sourceSize": {"w":16,"h":16}
},
"tile_floor_2.png":
{
	"frame": {"x":110,"y":0,"w":16,"h":16},
	"rotated": false,
	"trimmed": false,
	"spriteSourceSize": {"x":0,"y":0,"w":16,"h":16},
	"sourceSize": {"w":16,"h":16}
},
"tile_floor_3.png":
{
	"frame": {"x":270,"y":0,"w":16,"h":16},
	"rotated": false,
	"trimmed": false,
	"spriteSourceSize": {"x":0,"y":0,"w":16,"h":16},
	"sourceSize": {"w":16,"h":16}
},
"tile_menu_b.png":
{
	"frame": {"x":142,"y":0,"w":16,"h":16},
	"rotated": false,
	"trimmed": false,
	"spriteSourceSize": {"x":0,"y":0,"w":16,"h":16},
	"sourceSize": {"w":16,"h":16}
},
"tile_menu_bl.png":
{
	"frame": {"x":158,"y":0,"w":16,"h":16},
	"rotated": false,
	"trimmed": false,
	"spriteSourceSize": {"x":0,"y":0,"w":16,"h":16},
	"sourceSize": {"w":16,"h":16}
},
"tile_menu_br.png":
{
	"frame": {"x":190,"y":0,"w":16,"h":16},
	"rotated": false,
	"trimmed": false,
	"spriteSourceSize": {"x":0,"y":0,"w":16,"h":16},
	"sourceSize": {"w":16,"h":16}
},
"tile_menu_l.png":
{
	"frame": {"x":206,"y":0,"w":16,"h":16},
	"rotated": false,
	"trimmed": false,
	"spriteSourceSize": {"x":0,"y":0,"w":16,"h":16},
	"sourceSize": {"w":16,"h":16}
},
"tile_menu_r.png":
{
	"frame": {"x":238,"y":0,"w":16,"h":16},
	"rotated": false,
	"trimmed": false,
	"spriteSourceSize": {"x":0,"y":0,"w":16,"h":16},
	"sourceSize": {"w":16,"h":16}
},
"tile_menu_t.png":
{
	"frame": {"x":254,"y":0,"w":16,"h":16},
	"rotated": false,
	"trimmed": false,
	"spriteSourceSize": {"x":0,"y":0,"w":16,"h":16},
	"sourceSize": {"w":16,"h":16}
},
"tile_menu_ul.png":
{
	"frame": {"x":222,"y":0,"w":16,"h":16},
	"rotated": false,
	"trimmed": false,
	"spriteSourceSize": {"x":0,"y":0,"w":16,"h":16},
	"sourceSize": {"w":16,"h":16}
},
"tile_menu_ur.png":
{
	"frame": {"x":174,"y":0,"w":16,"h":16},
	"rotated": false,
	"trimmed": false,
	"spriteSourceSize": {"x":0,"y":0,"w":16,"h":16},
	"sourceSize": {"w":16,"h":16}
},
"tile_mountain_1.png":
{
	"frame": {"x":126,"y":0,"w":16,"h":16},
	"rotated": false,
	"trimmed": false,
	"spriteSourceSize": {"x":0,"y":0,"w":16,"h":16},
	"sourceSize": {"w":16,"h":16}
},
"tile_mountain_2.png":
{
	"frame": {"x":62,"y":0,"w":16,"h":16},
	"rotated": false,
	"trimmed": false,
	"spriteSourceSize": {"x":0,"y":0,"w":16,"h":16},
	"sourceSize": {"w":16,"h":16}
},
"tile_mountain_3.png":
{
	"frame": {"x":302,"y":0,"w":16,"h":16},
	"rotated": false,
	"trimmed": false,
	"spriteSourceSize": {"x":0,"y":0,"w":16,"h":16},
	"sourceSize": {"w":16,"h":16}
},
"tile_sky.png":
{
	"frame": {"x":78,"y":0,"w":16,"h":16},
	"rotated": false,
	"trimmed": false,
	"spriteSourceSize": {"x":0,"y":0,"w":16,"h":16},
	"sourceSize": {"w":16,"h":16}
},
"tile_water.png":
{
	"frame": {"x":94,"y":0,"w":16,"h":16},
	"rotated": false,
	"trimmed": false,
	"spriteSourceSize": {"x":0,"y":0,"w":16,"h":16},
	"sourceSize": {"w":16,"h":16}
},
"wizard_dead_1.png":
{
	"frame": {"x":160,"y":48,"w":32,"h":32},
	"rotated": false,
	"trimmed": false,
	"spriteSourceSize": {"x":0,"y":0,"w":32,"h":32},
	"sourceSize": {"w":32,"h":32}
},
"wizard_dead_2.png":
{
	"frame": {"x":224,"y":48,"w":32,"h":32},
	"rotated": false,
	"trimmed": false,
	"spriteSourceSize": {"x":0,"y":0,"w":32,"h":32},
	"sourceSize": {"w":32,"h":32}
},
"wizard_idle_1.png":
{
	"frame": {"x":288,"y":48,"w":32,"h":32},
	"rotated": false,
	"trimmed": false,
	"spriteSourceSize": {"x":0,"y":0,"w":32,"h":32},
	"sourceSize": {"w":32,"h":32}
},
"wizard_idle_2.png":
{
	"frame": {"x":256,"y":48,"w":32,"h":32},
	"rotated": false,
	"trimmed": false,
	"spriteSourceSize": {"x":0,"y":0,"w":32,"h":32},
	"sourceSize": {"w":32,"h":32}
},
"wizard_idle_3.png":
{
	"frame": {"x":192,"y":48,"w":32,"h":32},
	"rotated": false,
	"trimmed": false,
	"spriteSourceSize": {"x":0,"y":0,"w":32,"h":32},
	"sourceSize": {"w":32,"h":32}
},
"wizard_idle_4.png":
{
	"frame": {"x":128,"y":48,"w":32,"h":32},
	"rotated": false,
	"trimmed": false,
	"spriteSourceSize": {"x":0,"y":0,"w":32,"h":32},
	"sourceSize": {"w":32,"h":32}
},
"wizard_move_enemy_1.png":
{
	"frame": {"x":384,"y":16,"w":32,"h":32},
	"rotated": false,
	"trimmed": false,
	"spriteSourceSize": {"x":0,"y":0,"w":32,"h":32},
	"sourceSize": {"w":32,"h":32}
},
"wizard_move_enemy_2.png":
{
	"frame": {"x":32,"y":48,"w":32,"h":32},
	"rotated": false,
	"trimmed": false,
	"spriteSourceSize": {"x":0,"y":0,"w":32,"h":32},
	"sourceSize": {"w":32,"h":32}
},
"wizard_move_friendly_1.png":
{
	"frame": {"x":96,"y":48,"w":32,"h":32},
	"rotated": false,
	"trimmed": false,
	"spriteSourceSize": {"x":0,"y":0,"w":32,"h":32},
	"sourceSize": {"w":32,"h":32}
},
"wizard_move_friendly_2.png":
{
	"frame": {"x":64,"y":48,"w":32,"h":32},
	"rotated": false,
	"trimmed": false,
	"spriteSourceSize": {"x":0,"y":0,"w":32,"h":32},
	"sourceSize": {"w":32,"h":32}
},
"wizard_move_friendly_3.png":
{
	"frame": {"x":352,"y":16,"w":32,"h":32},
	"rotated": false,
	"trimmed": false,
	"spriteSourceSize": {"x":0,"y":0,"w":32,"h":32},
	"sourceSize": {"w":32,"h":32}
},
"wizard_move_friendly_4.png":
{
	"frame": {"x":256,"y":112,"w":32,"h":32},
	"rotated": false,
	"trimmed": false,
	"spriteSourceSize": {"x":0,"y":0,"w":32,"h":32},
	"sourceSize": {"w":32,"h":32}
}},
"meta": {
	"app": "http://www.codeandweb.com/texturepacker",
	"version": "1.0",
	"image": "textures.png",
	"format": "RGBA8888",
	"size": {"w":432,"h":432},
	"scale": "1",
	"smartupdate": "$TexturePacker:SmartUpdate:97c55c7c7874e0e1f94cb05a32bb5025:efd447ba4ceffacee26326a7adb2f0d7:cf827d152df04949dfee256cd0c8efd8$"
}
}
